bbqr.py
bbqr-0.2.0.dist-info/licenses/LICENSE
bbqr-0.2.0.dist-info/METADATA
bbqr-0.2.0.dist-info/WHEEL
bbqr-0.2.0.dist-info/entry_points.txt
bbqr-0.2.0.dist-info/top_level.txt
bbqr-0.2.0.dist-info/RECORD
