Metadata-Version: 2.4
Name: bbqr
Version: 0.2.0
Summary: 🔥 BBQR - The hottest terminal-based QR code generator that grills your data to perfection!
Home-page: https://github.com/foglomon/bbqr
Author: Ishman Singh
Project-URL: Bug Reports, https://github.com/foglomon/bbqr/issues
Project-URL: Source, https://github.com/foglomon/bbqr
Project-URL: Documentation, https://github.com/foglomon/bbqr#readme
Keywords: qr qrcode generator terminal cli bbq barcode wifi upload
Classifier: Development Status :: 4 - Beta
Classifier: Intended Audience :: Developers
Classifier: Intended Audience :: End Users/Desktop
Classifier: License :: OSI Approved :: MIT License
Classifier: Operating System :: OS Independent
Classifier: Programming Language :: Python :: 3
Classifier: Programming Language :: Python :: 3.7
Classifier: Programming Language :: Python :: 3.8
Classifier: Programming Language :: Python :: 3.9
Classifier: Programming Language :: Python :: 3.10
Classifier: Programming Language :: Python :: 3.11
Classifier: Programming Language :: Python :: 3.12
Classifier: Topic :: Utilities
Classifier: Topic :: Multimedia :: Graphics
Classifier: Topic :: Internet :: WWW/HTTP
Classifier: Topic :: System :: Networking
Classifier: Environment :: Console
Requires-Python: >=3.7
License-File: LICENSE
Requires-Dist: qrcode[pil]==8.0
Requires-Dist: Pillow==10.4.0
Requires-Dist: pyperclip==1.9.0
Requires-Dist: colorama==0.4.6
Requires-Dist: watchdog==4.0.1
Requires-Dist: pyzbar==0.1.9
Requires-Dist: requests==2.31.0
Dynamic: author
Dynamic: classifier
Dynamic: description
Dynamic: description-content-type
Dynamic: home-page
Dynamic: keywords
Dynamic: license-file
Dynamic: project-url
Dynamic: requires-dist
Dynamic: requires-python
Dynamic: summary
